./.env.sample
./.gitignore
./PKG-INFO
./README.md
./azure_user_mcp_server.py
./azure_user_mcp_server_test.py
./language.json
./makefile
./package_name
./push_info.json
./pyproject.toml
./simple_oauth_client_example.py
./uv.lock
./.devcontainer/devcontainer.json
./.devcontainer/post_create.sh
./assets/app-registration.png
./assets/mcp_oath_consent_screen.png
./assets/mcp_server_auth_entra_id_console.gif
./assets/mcp_server_auth_entra_id_inspector.gif
./assets/public-client-flows.png
./auth/__init__.py
./auth/auth_utilities.py
./auth/consent_dialog.py
./auth/entraid_auth_settings.py
./auth/entraid_oauth_provider.py
./auth/html/consent_dialog_page.html
./tools/azure_user_info_utility.py
iflow_mcp_sean_tate_fastmcp_python_oauth2_with_entra_id-0.1.0.dist-info/METADATA
iflow_mcp_sean_tate_fastmcp_python_oauth2_with_entra_id-0.1.0.dist-info/WHEEL
iflow_mcp_sean_tate_fastmcp_python_oauth2_with_entra_id-0.1.0.dist-info/entry_points.txt
iflow_mcp_sean_tate_fastmcp_python_oauth2_with_entra_id-0.1.0.dist-info/RECORD
