Metadata-Version: 2.4
Name: iflow-mcp_sean-tate_fastmcp-python-oauth2-with-entra-id
Version: 0.1.0
Summary: MCP Server Authorization Example using OAuth2 with Microsoft Entra ID
Project-URL: Homepage, https://github.com/yourusername/fastmcp-python-oauth2-with-entra-id
Project-URL: Repository, https://github.com/yourusername/fastmcp-python-oauth2-with-entra-id
Project-URL: Documentation, https://github.com/yourusername/fastmcp-python-oauth2-with-entra-id/blob/main/README.md
Project-URL: Issues, https://github.com/yourusername/fastmcp-python-oauth2-with-entra-id/issues
Author-email: Your Name <your.email@example.com>
License: MIT
Classifier: Development Status :: 4 - Beta
Classifier: Intended Audience :: Developers
Classifier: License :: OSI Approved :: MIT License
Classifier: Programming Language :: Python :: 3.11
Classifier: Programming Language :: Python :: 3.12
Requires-Python: >=3.11
Requires-Dist: fastmcp==2.5.1
Requires-Dist: httpx>=0.24.0
Requires-Dist: pydantic-settings>=2.0.0
Requires-Dist: pydantic>=2.0.0
Requires-Dist: python-dotenv>=0.19.0
Requires-Dist: requests>=2.25.0
Provides-Extra: dev
Requires-Dist: black>=23.0.0; extra == 'dev'
Requires-Dist: flake8>=6.0.0; extra == 'dev'
Requires-Dist: isort>=5.12.0; extra == 'dev'
Requires-Dist: mypy>=1.0.0; extra == 'dev'
Requires-Dist: pre-commit>=3.0.0; extra == 'dev'
Requires-Dist: pytest-asyncio>=0.21.0; extra == 'dev'
Requires-Dist: pytest>=7.0.0; extra == 'dev'
